discord_handler/DiscordHandler.py
discord_handler/__init__.py
discord_handler-0.0.3.dist-info/LICENSE
discord_handler-0.0.3.dist-info/METADATA
discord_handler-0.0.3.dist-info/WHEEL
discord_handler-0.0.3.dist-info/top_level.txt
discord_handler-0.0.3.dist-info/RECORD
