Metadata-Version: 2.1
Name: discord-handler
Version: 0.0.3
Summary: A small discord handler for the logging module using webtokens
Home-page: https://github.com/traysercassa/DiscordHandler
Author: Traysercassa
Author-email: 
License: UNKNOWN
Platform: UNKNOWN
Classifier: Programming Language :: Python :: 3
Classifier: License :: OSI Approved :: MIT License
Classifier: Operating System :: OS Independent
Classifier: Topic :: System :: Logging
Requires-Python: >=3
License-File: LICENSE
Requires-Dist: requests
